setup.py
pp_sqlalchemy/__init__.py
pypoly_tool_sqlalchemy.egg-info/PKG-INFO
pypoly_tool_sqlalchemy.egg-info/SOURCES.txt
pypoly_tool_sqlalchemy.egg-info/dependency_links.txt
pypoly_tool_sqlalchemy.egg-info/entry_points.txt
pypoly_tool_sqlalchemy.egg-info/top_level.txt